{
  "byte_length": 1657332,
  "company_slug": "paypal",
  "content_type": "text/html; charset=utf-8",
  "fetched_at": "2026-07-20T08:47:44.559568+00:00",
  "http_status": 200,
  "policy_kind": "privacy_policy",
  "policy_label": "PayPal Privacy Statement (US)",
  "policy_region": "US",
  "sha256": "38c2f05057517a62d72f86863ad618d6e33f99e84ecd23b3ccc2e2946e7f214f",
  "snapshot_date": "2026-07-20",
  "source": "live",
  "text_length": 43077,
  "url": "https://www.paypal.com/us/legalhub/privacy-full"
}
