{
  "byte_length": 15684,
  "company_slug": "adobe",
  "content_type": "text/html; charset=utf-8",
  "fetched_at": "2026-07-08T08:15:50.237620+00:00",
  "http_status": 200,
  "policy_kind": "ai_terms",
  "policy_label": "Adobe Generative AI User Guidelines",
  "policy_region": null,
  "sha256": "13eb6980294a9dca3df65e8ca7aff1d677acb58c609b12def305b3dd11bea962",
  "snapshot_date": "2026-07-08",
  "source": "live",
  "text_length": 4637,
  "url": "https://www.adobe.com/legal/licenses-terms/adobe-gen-ai-user-guidelines.html"
}
